wilma/__init__.py
wilma/__main__.py
wilma/checker.py
wilma/config.py
wilma/enums.py
wilma/reports.py
wilma/utils.py
wilma/checks/__init__.py
wilma/checks/agents.py
wilma/checks/fine_tuning.py
wilma/checks/genai.py
wilma/checks/guardrails.py
wilma/checks/iam.py
wilma/checks/knowledge_bases.py
wilma/checks/logging.py
wilma/checks/network.py
wilma/checks/tagging.py
wilma_sec-1.1.0.dist-info/licenses/LICENSE
wilma_sec-1.1.0.dist-info/METADATA
wilma_sec-1.1.0.dist-info/WHEEL
wilma_sec-1.1.0.dist-info/entry_points.txt
wilma_sec-1.1.0.dist-info/top_level.txt
wilma_sec-1.1.0.dist-info/RECORD
