Metadata-Version: 2.4
Name: wilma-sec
Version: 1.1.0
Summary: Wilma - AWS Bedrock Security Configuration Checker with GenAI-specific security features
Home-page: https://github.com/ethanolivertroy/wilma
Author: Ethan Troy
Author-email: 
License: GPL-3.0-or-later
Project-URL: Homepage, https://github.com/ethanolivertroy/wilma
Project-URL: Bug Tracker, https://github.com/ethanolivertroy/wilma/issues
Project-URL: Documentation, https://github.com/ethanolivertroy/wilma#readme
Keywords: aws,bedrock,security,genai,ai,ml,audit,compliance,wilma
Classifier: Development Status :: 4 - Beta
Classifier: Intended Audience :: Developers
Classifier: Intended Audience :: System Administrators
Classifier: Topic :: Security
Classifier: Topic :: System :: Systems Administration
Classifier: License :: OSI Approved :: GNU General Public License v3 or later (GPLv3+)
Classifier: Programming Language :: Python :: 3
Classifier: Programming Language :: Python :: 3.8
Classifier: Programming Language :: Python :: 3.9
Classifier: Programming Language :: Python :: 3.10
Classifier: Programming Language :: Python :: 3.11
Classifier: Programming Language :: Python :: 3.12
Classifier: Operating System :: OS Independent
Requires-Python: >=3.8
License-File: LICENSE
Requires-Dist: boto3>=1.34.0
Requires-Dist: botocore>=1.34.0
Requires-Dist: colorama>=0.4.6
Requires-Dist: tabulate>=0.9.0
Requires-Dist: pyyaml>=6.0.0
Dynamic: home-page
Dynamic: license-file
Dynamic: requires-python
